exam_kernel/__init__.py
exam_kernel/__main__.py
exam_kernel/__version__.py
exam_kernel/install.py
exam_kernel/kernel.json
exam_kernel/kernel.py
exam_kernel-0.2.0.dist-info/METADATA
exam_kernel-0.2.0.dist-info/WHEEL
exam_kernel-0.2.0.dist-info/licenses/LICENSE
exam_kernel-0.2.0.dist-info/RECORD
