Metadata-Version: 2.1
Name: exam_kernel
Version: 0.2.0
Summary: A restricted configurable Python kernel for exams
Project-URL: Documentation, https://exam-kernel.readthedocs.io
Project-URL: Issues, https://github.com/Digiklausur/exam_kernel/issues
Project-URL: Source, https://github.com/Digiklausur/exam_kernel
Project-URL: Pypi, https://pypi.org/project/exam-kernel/
Author-email: Tim Metzler <tim.metzler@h-brs.de>
License-Expression: MIT
License-File: LICENSE
Classifier: Programming Language :: Python
Classifier: Programming Language :: Python :: 3
Classifier: Programming Language :: Python :: 3.7
Classifier: Programming Language :: Python :: 3.8
Classifier: Programming Language :: Python :: 3.9
Requires-Python: >3.7
Requires-Dist: ipykernel
Requires-Dist: ipython
Requires-Dist: jupyter-client
Provides-Extra: dev
Requires-Dist: hatchling; extra == 'dev'
Requires-Dist: pre-commit; extra == 'dev'
Requires-Dist: pydata-sphinx-theme; extra == 'dev'
Requires-Dist: sphinx; extra == 'dev'
Requires-Dist: tbump; extra == 'dev'
